MANIFEST.in
README.md
setup.py
basecamp/__init__.py
basecamp/basecamp.py
basecamp.egg-info/PKG-INFO
basecamp.egg-info/SOURCES.txt
basecamp.egg-info/dependency_links.txt
basecamp.egg-info/requires.txt
basecamp.egg-info/top_level.txt