Metadata-Version: 1.0
Name: basecamp
Version: 0.0.12
Summary: Almost complete warapper around the Basecamp API. 
Home-page: https://github.com/nowherefarm/basecamp
Author: Matias Saguir
Author-email: mativs@gmail.com
License: MIT
Keywords: basecamp api
Platform: UNKNOWN
Classifier: Development Status :: 3 - Alpha
Classifier: Intended Audience :: Developers
Classifier: License :: OSI Approved :: MIT License
Classifier: Natural Language :: English
Classifier: Operating System :: OS Independent
Classifier: Programming Language :: Python :: 2.7
Classifier: Topic :: Software Development :: Bug Tracking
